f4pga/fpga-project/app/project2/alu.v
`timescale 1ns / 1ps

module alu #(parameter w = 8)
(
    input [w-1:0]A, B,
    input [2:0] op,
    output reg [w-1:0] y,
    output reg zero, negative, carry, overflow
    
);
    reg [w:0] temp;
    always @(*)
    begin
        // Default assignments to avoid latches
        y = 0;
        temp = 0;
        carry = 0;
        overflow = 0;
        
        case (op)
            3'd0: y = A & B;          
            3'd1: y = A | B;          
            3'd2: y = A ^ B;
            3'd3: begin               
                temp  = {1'b0,A} + {1'b0,B};
                y     = temp[w-1:0];
                carry = temp[w];
                overflow = (~(A[w-1] ^ B[w-1])) & (y[w-1] ^ A[w-1]);
            end
            3'd4: begin               
                temp  = {1'b0,A} + {1'b0,(~B)} + 1'b1;
                y     = temp[w-1:0];
                carry = temp[w];  
                overflow = (A[w-1] ^ B[w-1]) & (y[w-1] ^ A[w-1]);
            end         
            3'd5: y = A << 1;         
            3'd6: y = A >> 1;        
            3'd7: y = A;  
            default: y = 0;   
        endcase
        zero = (y == 0);
        negative = y[w-1];
    end 
    

endmodule

app/project2/alu_tb.v
`timescale 1ns / 1ps

module tb_alu;
    parameter w        = 8;
    parameter NUM_RAND = 10000;
    reg  [w-1:0] A, B;
    reg  [2:0]   op;
    wire [w-1:0] y;
    wire         zero, negative, carry, overflow;
    alu #(.w(w)) dut (
        .A(A), .B(B), .op(op),
        .y(y),
        .zero(zero), .negative(negative),
        .carry(carry), .overflow(overflow)
    );
    reg [w-1:0] exp_y;
    reg         exp_zero, exp_negative, exp_carry, exp_overflow;
    reg [w:0]   temp_ref;

    integer pass_count;
    integer fail_count;
    integer i;
    integer rand_a, rand_b, rand_op;
    initial begin
        $dumpfile("alu_waves.vcd");
        $dumpvars(0, tb_alu);
    end
    task reference_model;
        input [w-1:0] a_in, b_in;
        input [2:0]   op_in;
    begin
        exp_carry    = 1'b0;
        exp_overflow = 1'b0;
        temp_ref     = {(w+1){1'b0}};

        case (op_in)
            3'd0: exp_y = a_in & b_in;
            3'd1: exp_y = a_in | b_in;
            3'd2: exp_y = a_in ^ b_in;

            3'd3: begin  // ADD
                temp_ref     = {1'b0, a_in} + {1'b0, b_in};
                exp_y        = temp_ref[w-1:0];
                exp_carry    = temp_ref[w];
                exp_overflow = (~(a_in[w-1] ^ b_in[w-1])) & (exp_y[w-1] ^ a_in[w-1]);
            end

            3'd4: begin  // SUB
                temp_ref     = {1'b0, a_in} + {1'b0, ~b_in} + {{w{1'b0}}, 1'b1};
                exp_y        = temp_ref[w-1:0];
                exp_carry    = temp_ref[w];
                exp_overflow = (a_in[w-1] ^ b_in[w-1]) & (exp_y[w-1] ^ a_in[w-1]);
            end

            3'd5: begin  // SHL
                exp_carry = a_in[w-1];
                exp_y     = a_in << 1;
            end

            3'd6: begin  // SHR
                exp_carry = a_in[0];
                exp_y     = a_in >> 1;
            end

            3'd7: exp_y = a_in;  // PASS A

            default: exp_y = {w{1'b0}};
        endcase

        exp_zero     = (exp_y == {w{1'b0}});
        exp_negative = exp_y[w-1];
    end
    endtask
    task check;
        input [w-1:0] a_in, b_in;
        input [2:0]   op_in;
        input integer test_num;
        input [8*8:1] label;
    begin
        A  = a_in;
        B  = b_in;
        op = op_in;
        #10;

        reference_model(a_in, b_in, op_in);

        if (y        !== exp_y        ||
            zero     !== exp_zero     ||
            negative !== exp_negative ||
            carry    !== exp_carry    ||
            overflow !== exp_overflow)
        begin
            fail_count = fail_count + 1;
            $display("FAIL [%0d] %-8s | A=0x%02h B=0x%02h op=%0d",
                     test_num, label, a_in, b_in, op_in);
            $display("         Got : y=0x%02h Z=%b N=%b C=%b V=%b",
                     y, zero, negative, carry, overflow);
            $display("         Exp : y=0x%02h Z=%b N=%b C=%b V=%b",
                     exp_y, exp_zero, exp_negative, exp_carry, exp_overflow);
            $finish;
        end else begin
            pass_count = pass_count + 1;
        end
    end
    endtask
    initial begin
        pass_count = 0;
        fail_count = 0;
        A = 0; B = 0; op = 0;
        #5;

        $display("============================================");
        $display("   ALU Self-Checking Testbench             ");
        $display("   W = %0d bits                            ", w);
        $display("============================================");
        $display("--- Directed Edge Cases ---");
        // AND
        check(8'h00, 8'hFF, 3'd0,  1, "AND");
        check(8'hFF, 8'hFF, 3'd0,  2, "AND");
        check(8'hAA, 8'h55, 3'd0,  3, "AND");
        check(8'hFF, 8'h00, 3'd0,  4, "AND");
        // OR
        check(8'h00, 8'hFF, 3'd1,  5, "OR");
        check(8'hAA, 8'h55, 3'd1,  6, "OR");
        check(8'h00, 8'h00, 3'd1,  7, "OR");
        // XOR
        check(8'hFF, 8'hFF, 3'd2,  8, "XOR");
        check(8'hAA, 8'h55, 3'd2,  9, "XOR");
        check(8'h00, 8'h00, 3'd2, 10, "XOR");
        // ADD normal
        check(8'h00, 8'h00, 3'd3, 11, "ADD");
        check(8'h01, 8'h01, 3'd3, 12, "ADD");
        check(8'hFE, 8'h01, 3'd3, 13, "ADD");
        // ADD carry out
        check(8'hFF, 8'h01, 3'd3, 14, "ADD");
        check(8'hFF, 8'hFF, 3'd3, 15, "ADD");
        // ADD overflow pos+pos=neg
        check(8'h7F, 8'h01, 3'd3, 16, "ADD");
        check(8'h40, 8'h40, 3'd3, 17, "ADD");
        // ADD overflow neg+neg=pos
        check(8'h80, 8'h80, 3'd3, 18, "ADD");
        // SUB normal
        check(8'h01, 8'h01, 3'd4, 19, "SUB");
        check(8'hFF, 8'h01, 3'd4, 20, "SUB");
        check(8'hFF, 8'hFF, 3'd4, 21, "SUB");
        // SUB borrow
        check(8'h00, 8'h01, 3'd4, 22, "SUB");
        check(8'h01, 8'hFF, 3'd4, 23, "SUB");
        // SUB overflow pos-neg=neg
        check(8'h7F, 8'hFF, 3'd4, 24, "SUB");
        // SUB overflow neg-pos=pos
        check(8'h80, 8'h01, 3'd4, 25, "SUB");
        // SHL
        check(8'h01, 8'h00, 3'd5, 26, "SHL");
        check(8'h80, 8'h00, 3'd5, 27, "SHL");
        check(8'hFF, 8'h00, 3'd5, 28, "SHL");
        check(8'h40, 8'h00, 3'd5, 29, "SHL");
        // SHR
        check(8'h01, 8'h00, 3'd6, 30, "SHR");
        check(8'h80, 8'h00, 3'd6, 31, "SHR");
        check(8'hFF, 8'h00, 3'd6, 32, "SHR");
        check(8'h02, 8'h00, 3'd6, 33, "SHR");
        // PASS A
        check(8'h00, 8'h00, 3'd7, 34, "PASS");
        check(8'hAB, 8'h00, 3'd7, 35, "PASS");
        check(8'hFF, 8'h00, 3'd7, 36, "PASS");
        check(8'h80, 8'h00, 3'd7, 37, "PASS");

        $display("  Directed tests passed: %0d", pass_count);
        $display("--- Randomized Tests (%0d vectors) ---", NUM_RAND);

        for (i = 0; i < NUM_RAND; i = i + 1) begin
            rand_a  = $random;
            rand_b  = $random;
            rand_op = $random % 8;
            if (rand_op < 0) rand_op = -rand_op;

            check(rand_a[7:0], rand_b[7:0], rand_op[2:0], 100 + i, "RAND");
        end
        $display("  Random tests passed: %0d", pass_count - 37);
        $display("============================================");
        if (fail_count == 0)
            $display("RESULT: PASS  (%0d vectors checked)", pass_count);
        else
            $display("RESULT: FAIL  (%0d/%0d failed)", fail_count, pass_count + fail_count);
        $display("============================================");

        $finish;
    end

endmodule

fpga-project/app/project2/alu_waves.vcd
$date
	Sat Feb 21 19:58:56 2026
$end
$version
	Icarus Verilog
$end
$timescale
	1ps
$end
$scope module tb_alu $end
$var wire 1 ! zero $end
$var wire 8 " y [7:0] $end
$var wire 1 # overflow $end
$var wire 1 $ negative $end
$var wire 1 % carry $end
$var parameter 32 & NUM_RAND $end
$var parameter 32 ' w $end
$var reg 8 ( A [7:0] $end
$var reg 8 ) B [7:0] $end
$var reg 1 * exp_carry $end
$var reg 1 + exp_negative $end
$var reg 1 , exp_overflow $end
$var reg 8 - exp_y [7:0] $end
$var reg 1 . exp_zero $end
$var reg 3 / op [2:0] $end
$var reg 9 0 temp_ref [8:0] $end
$var integer 32 1 fail_count [31:0] $end
$var integer 32 2 i [31:0] $end
$var integer 32 3 pass_count [31:0] $end
$var integer 32 4 rand_a [31:0] $end
$var integer 32 5 rand_b [31:0] $end
$var integer 32 6 rand_op [31:0] $end
$scope module dut $end
$var wire 8 7 A [7:0] $end
$var wire 8 8 B [7:0] $end
$var wire 3 9 op [2:0] $end
$var parameter 32 : w $end
$var reg 1 % carry $end
$var reg 1 $ negative $end
$var reg 1 # overflow $end
$var reg 9 ; temp [8:0] $end
$var reg 8 < y [7:0] $end
$var reg 1 ! zero $end
$upscope $end
$scope task check $end
$var reg 8 = a_in [7:0] $end
$var reg 8 > b_in [7:0] $end
$var reg 64 ? label [64:1] $end
$var reg 3 @ op_in [2:0] $end
$var integer 32 A test_num [31:0] $end
$upscope $end
$scope task reference_model $end
$var reg 8 B a_in [7:0] $end
$var reg 8 C b_in [7:0] $end
$var reg 3 D op_in [2:0] $end
$upscope $end
$upscope $end
$enddefinitions $end
$comment Show the parameter values. $end
$dumpall
b1000 :
b1000 '
b10011100010000 &
$end
#0
$dumpvars
bx D
bx C
bx B
bx A
bx @
bx ?
bx >
bx =
b0 <
b0 ;
b0 9
b0 8
b0 7
bx 6
bx 5
bx 4
b0 3
bx 2
b0 1
bx 0
b0 /
x.
bx -
x,
x+
x*
b0 )
b0 (
0%
0$
0#
b0 "
1!
$end
#5000
b11111111 )
b11111111 8
b10000010100111001000100 ?
b1 A
b0 @
b11111111 >
b0 =
#15000
1$
0!
b11111111 "
b11111111 <
b11111111 (
b11111111 7
b10 A
b11111111 =
b1 3
0+
1.
b0 -
b0 0
0,
0*
b0 D
b11111111 C
b0 B
#25000
0$
1!
b0 "
b0 <
b1010101 )
b1010101 8
b10101010 (
b10101010 7
b11 A
b1010101 >
b10101010 =
b10 3
1+
0.
b11111111 -
b11111111 B
#35000
b0 )
b0 8
b11111111 (
b11111111 7
b100 A
b0 >
b11111111 =
b11 3
0+
1.
b0 -
b1010101 C
b10101010 B
#45000
1$
0!
b11111111 "
b11111111 <
b1 /
b1 9
b11111111 )
b11111111 8
b0 (
b0 7
b100111101010010 ?
b101 A
b1 @
b11111111 >
b0 =
b100 3
b0 C
b11111111 B
#55000
b11111111 "
b11111111 <
b1010101 )
b1010101 8
b10101010 (
b10101010 7
b110 A
b1010101 >
b10101010 =
b101 3
1+
0.
b11111111 -
b1 D
b11111111 C
b0 B
#65000
0$
1!
b0 "
b0 <
b0 )
b0 8
b0 (
b0 7
b111 A
b0 >
b0 =
b110 3
b1010101 C
b10101010 B
#75000
b10 /
b10 9
b11111111 )
b11111111 8
b11111111 (
b11111111 7
b10110000100111101010010 ?
b1000 A
b10 @
b11111111 >
b11111111 =
b111 3
0+
1.
b0 -
b0 C
b0 B
#85000
1$
0!
b11111111 "
b11111111 <
b1010101 )
b1010101 8
b10101010 (
b10101010 7
b1001 A
b1010101 >
b10101010 =
b1000 3
b10 D
b11111111 C
b11111111 B
#95000
0$
1!
b0 "
b0 <
b0 )
b0 8
b0 (
b0 7
b1010 A
b0 >
b0 =
b1001 3
1+
0.
b11111111 -
b1010101 C
b10101010 B
#105000
b11 /
b11 9
b10000010100010001000100 ?
b1011 A
b11 @
b1010 3
0+
1.
b0 -
b0 C
b0 B
#115000
0!
b10 "
b10 <
b10 ;
b1 )
b1 8
b1 (
b1 7
b1100 A
b1 >
b1 =
b1011 3
b11 D
#125000
1$
b11111111 ;
b11111111 "
b11111111 <
b11111110 (
b11111110 7
b1101 A
b11111110 =
b1100 3
0.
b10 -
b10 0
b1 C
b1 B
#135000
0$
1!
1%
b100000000 ;
b0 "
b0 <
b11111111 (
b11111111 7
b1110 A
b11111111 =
b1101 3
1+
b11111111 -
b11111111 0
b11111110 B
#145000
1$
0!
b11111110 "
b11111110 <
1%
b111111110 ;
b11111111 )
b11111111 8
b1111 A
b11111111 >
b1110 3
0+
1.
1*
b0 -
b100000000 0
b11111111 B
#155000
1#
0%
b10000000 ;
b10000000 "
b10000000 <
b1 )
b1 8
b1111111 (
b1111111 7
b10000 A
b1 >
b1111111 =
b1111 3
1+
0.
b11111110 -
b111111110 0
1*
b11111111 C
#165000
1#
b10000000 ;
b10000000 "
b10000000 <
b1000000 )
b1000000 8
b1000000 (
b1000000 7
b10001 A
b1000000 >
b1000000 =
b10000 3
1,
b10000000 -
b10000000 0
0*
b1 C
b1111111 B
#175000
0$
1!
1%
1#
b100000000 ;
b0 "
b0 <
b10000000 )
b10000000 8
b10000000 (
b10000000 7
b10010 A
b10000000 >
b10000000 =
b10001 3
b10000000 0
1,
b1000000 C
b1000000 B
#185000
0#
1%
b100000000 ;
b100 /
b100 9
b1 )
b1 8
b1 (
b1 7
b10100110101010101000010 ?
b10011 A
b100 @
b1 >
b1 =
b10010 3
0+
1.
1*
b0 -
b100000000 0
1,
b10000000 C
b10000000 B
#195000
1$
0!
b11111110 "
b11111110 <
1%
b111111110 ;
b11111111 (
b11111111 7
b10100 A
b11111111 =
b10011 3
b100000000 0
0,
1*
b100 D
b1 C
b1 B
#205000
0$
1!
1%
b100000000 ;
b0 "
b0 <
b11111111 )
b11111111 8
b10101 A
b11111111 >
b10100 3
1+
0.
b11111110 -
b111111110 0
1*
b11111111 B
#215000
1$
0!
b11111111 "
b11111111 <
0%
b11111111 ;
b1 )
b1 8
b0 (
b0 7
b10110 A
b1 >
b0 =
b10101 3
0+
1.
b0 -
b100000000 0
1*
b11111111 C
#225000
0$
b10 ;
b10 "
b10 <
b11111111 )
b11111111 8
b1 (
b1 7
b10111 A
b11111111 >
b1 =
b10110 3
1+
0.
b11111111 -
b11111111 0
0*
b1 C
b0 B
#235000
1$
1#
b10000000 ;
b10000000 "
b10000000 <
b1111111 (
b1111111 7
b11000 A
b1111111 =
b10111 3
0+
b10 -
b10 0
b11111111 C
b1 B
#245000
0$
1%
1#
b101111111 ;
b1111111 "
b1111111 <
b1 )
b1 8
b10000000 (
b10000000 7
b11001 A
b1 >
b10000000 =
b11000 3
1+
1,
b10000000 -
b10000000 0
b1111111 B
#255000
0#
0%
b0 ;
b10 "
b10 <
b101 /
b101 9
b0 )
b0 8
b1 (
b1 7
b10100110100100001001100 ?
b11010 A
b101 @
b0 >
b1 =
b11001 3
0+
1*
b1111111 -
b101111111 0
1,
b1 C
b10000000 B
#265000
1!
1%
b0 "
b0 <
b10000000 (
b10000000 7
b11011 A
b10000000 =
b11010 3
b10 -
b0 0
0,
0*
b101 D
b0 C
b1 B
#275000
1$
0!
b11111110 "
b11111110 <
1%
b11111111 (
b11111111 7
b11100 A
b11111111 =
b11011 3
1.
b0 -
1*
b10000000 B
#285000
0%
b10000000 "
b10000000 <
b1000000 (
b1000000 7
b11101 A
b1000000 =
b11100 3
1+
0.
b11111110 -
1*
b11111111 B
#295000
0$
1!
1%
b0 "
b0 <
b110 /
b110 9
b1 (
b1 7
b10100110100100001010010 ?
b11110 A
b110 @
b1 =
b11101 3
b10000000 -
0*
b1000000 B
#305000
0!
b1000000 "
b1000000 <
0%
b10000000 (
b10000000 7
b11111 A
b10000000 =
b11110 3
0+
1.
b0 -
1*
b110 D
b1 B
#315000
1%
b1111111 "
b1111111 <
b11111111 (
b11111111 7
b100000 A
b11111111 =
b11111 3
0.
b1000000 -
0*
b10000000 B
#325000
0%
b1 "
b1 <
b10 (
b10 7
b100001 A
b10 =
b100000 3
b1111111 -
1*
b11111111 B
#335000
1!
b0 "
b0 <
b111 /
b111 9
b0 (
b0 7
b1010000010000010101001101010011 ?
b100010 A
b111 @
b0 =
b100001 3
b1 -
0*
b10 B
#345000
1$
0!
b10101011 "
b10101011 <
b10101011 (
b10101011 7
b100011 A
b10101011 =
b100010 3
1.
b0 -
b111 D
b0 B
#355000
b11111111 "
b11111111 <
b11111111 (
b11111111 7
b100100 A
b11111111 =
b100011 3
1+
0.
b10101011 -
b10101011 B
#365000
b10000000 "
b10000000 <
b10000000 (
b10000000 7
b100101 A
b10000000 =
b100100 3
b11111111 -
b11111111 B
#375000
0$
b100100 "
b100100 <
b10000001 )
b10000001 8
b100100 (
b100100 7
b1010010010000010100111001000100 ?
b1100100 A
b10000001 >
b100100 =
b111 6
b11000000100010010101111010000001 5
b10010000101010011010100100100 4
b0 2
b100101 3
b10000000 -
b10000000 B
#385000
1$
b11000110 "
b11000110 <
b101 /
b101 9
b1101 )
b1101 8
b1100011 (
b1100011 7
b1100101 A
b101 @
b1101 >
b1100011 =
b101 6
b110101110010111101100001101 5
b10110001111100000101011001100011 4
b1 2
b100110 3
0+
b100100 -
b10000001 C
b100100 B
#395000
0$
b1110111 "
b1110111 <
b1 /
b1 9
b10010 )
b10010 8
b1100101 (
b1100101 7
b1100110 A
b1 @
b10010 >
b1100101 =
b1 6
b10001001001101110101001000010010 5
b10110010110000101000010001100101 4
b10 2
b100111 3
1+
b11000110 -
b101 D
b1101 C
b1100011 B
#405000
b11010 "
b11010 <
b101 /
b101 9
b1110110 )
b1110110 8
b1101 (
b1101 7
b1100111 A
b101 @
b1110110 >
b1101 =
b101 6
b111011001000111111000101110110 5
b110110101111100110100001101 4
b11 2
b101000 3
0+
b1110111 -
b1 D
b10010 C
b1100101 B
#415000
1$
b11101101 "
b11101101 <
b1 /
b1 9
b10001100 )
b10001100 8
b11101101 (
b11101101 7
b1101000 A
b1 @
b10001100 >
b11101101 =
b1 6
b1000110001011011111011110001100 5
b1110110110101000101011111101101 4
b100 2
b101001 3
b11010 -
b101 D
b1110110 C
b1101 B
#425000
0$
b1100011 "
b1100011 <
b110 /
b110 9
b11000101 )
b11000101 8
b11000110 (
b11000110 7
b1101001 A
b110 @
b11000101 >
b11000110 =
b110 6
b11100010111101111000010011000101 5
b11100011001101110010010011000110 4
b101 2
b101010 3
1+
b11101101 -
b1 D
b10001100 C
b11101101 B
#435000
1%
b1110010 "
b1110010 <
b1110111 )
b1110111 8
b11100101 (
b11100101 7
b1101010 A
b1110111 >
b11100101 =
b110 6
b10111011110100100111001001110111 5
b1110010101011111111011111100101 4
b110 2
b101011 3
0+
b1100011 -
b110 D
b11000101 C
b11000110 B
#445000
0%
b1111101 "
b1111101 <
b10 /
b10 9
b11110010 )
b11110010 8
b10001111 (
b10001111 7
b1101011 A
b10 @
b11110010 >
b10001111 =
b10 6
b1111001001100000110100111110010 5
b1000111111011001101101110001111 4
b111 2
b101100 3
b1110010 -
1*
b1110111 C
b11100101 B
#455000
1%
b100100011 ;
b100011 "
b100011 <
b100 /
b100 9
b11000101 )
b11000101 8
b11101000 (
b11101000 7
b1101100 A
b100 @
b11000101 >
b11101000 =
b100 6
b11100010110010100100111011000101 5
b11110100000000000111101011101000 4
b1000 2
b101101 3
b1111101 -
0*
b10 D
b11110010 C
b10001111 B
#465000
1$
0%
b11101010 ;
b11101010 "
b11101010 <
b11 /
b11 9
b101101 )
b101101 8
b10111101 (
b10111101 7
b1101101 A
b11 @
b101101 >
b10111101 =
b11 6
b10010110101010110101100000101101 5
b11011110100011100010100010111101 4
b1001 2
b101110 3
1*
b100011 -
b100100011 0
b100 D
b11000101 C
b11101000 B
#475000
0$
b0 ;
b10 "
b10 <
b0 /
b0 9
b1010 )
b1010 8
b1100011 (
b1100011 7
b1101110 A
b0 @
b1010 >
b1100011 =
b0 6
b101011100111000011100001010 5
b10110001111011110110001001100011 4
b1010 2
b101111 3
1+
b11101010 -
b11101010 0
0*
b11 D
b101101 C
b10111101 B
#485000
1$
b11001010 ;
b11001010 "
b11001010 <
b11 /
b11 9
b10101010 )
b10101010 8
b100000 (
b100000 7
b1101111 A
b11 @
b10101010 >
b100000 =
b11 6
b1010101011110000100010110101010 5
b10000011001000010000100100000 4
b1011 2
b110000 3
0+
b10 -
b0 0
b0 D
b1010 C
b1100011 B
#495000
b10101001 ;
b10101001 "
b10101001 <
b10011 )
b10011 8
b10010110 (
b10010110 7
b1110000 A
b10011 >
b10010110 =
b11 6
b10001001100000111011100000010011 5
b11001011001000000011111010010110 4
b1100 2
b110001 3
1+
b11001010 -
b11001010 0
b11 D
b10101010 C
b100000 B
#505000
1#
b10111110 ;
b10111110 "
b10111110 <
b1101011 )
b1101011 8
b1010011 (
b1010011 7
b1110001 A
b1101011 >
b1010011 =
b11 6
b110101100111111101110101101011 5
b10101001101001111101011001010011 4
b1101 2
b110010 3
b10101001 -
b10101001 0
b10011 C
b10010110 B
#515000
0$
0#
b0 ;
b100 "
b100 <
b101 /
b101 9
b10101110 )
b10101110 8
b10 (
b10 7
b1110010 A
b101 @
b10101110 >
b10 =
b101 6
b11010111010101100011111010101110 5
b10000001000101110100101000000010 4
b1110 2
b110011 3
1,
b10111110 -
b10111110 0
b1101011 C
b1010011 B
#525000
1$
b11101100 "
b11101100 <
b10 /
b10 9
b100011 )
b100011 8
b11001111 (
b11001111 7
b1110011 A
b10 @
b100011 >
b11001111 =
b10 6
b10001100001000100100100100011 5
b11100111110001010111001011001111 4
b1111 2
b110100 3
0+
b100 -
b0 0
0,
b101 D
b10101110 C
b10 B
#535000
b11110110 "
b11110110 <
b111100 )
b111100 8
b11001010 (
b11001010 7
b1110100 A
b111100 >
b11001010 =
b10011110001100010100110000111100 5
b11100101011100110000101011001010 4
b10000 2
b110101 3
1+
b11101100 -
b10 D
b100011 C
b11001111 B
#545000
0$
1!
b0 "
b0 <
b0 /
b0 9
b1000001 )
b1000001 8
b10001010 (
b10001010 7
b1110101 A
b0 @
b1000001 >
b10001010 =
b0 6
b100000110001001011001101000001 5
b1000101001011100110000110001010 4
b10001 2
b110110 3
b11110110 -
b111100 C
b11001010 B
#555000
0!
1%
b1 "
b1 <
b100000001 ;
b11 /
b11 9
b10001001 )
b10001001 8
b1111000 (
b1111000 7
b1110110 A
b11 @
b10001001 >
b1111000 =
b11 6
b11000100100010100001001010001001 5
b111100001000001111001101111000 4
b10010 2
b110111 3
0+
1.
b0 -
b0 D
b1000001 C
b10001010 B
#565000
0%
b0 ;
b1011011 "
b1011011 <
b110 /
b110 9
b11000110 )
b11000110 8
b10110110 (
b10110110 7
b1110111 A
b110 @
b11000110 >
b10110110 =
b110 6
b1100011010010111111100111000110 5
b1011011000000100110010110110110 4
b10011 2
b111000 3
0.
1*
b1 -
b100000001 0
b11 D
b10001001 C
b1111000 B
#575000
1%
b1111000 "
b1111000 <
b101 /
b101 9
b101010 )
b101010 8
b10111100 (
b10111100 7
b1111000 A
b101 @
b101010 >
b10111100 =
b101 6
b10101000011111101110100101010 5
b11011110011101010000001010111100 4
b10100 2
b111001 3
b1011011 -
b0 0
0*
b110 D
b11000110 C
b10110110 B
#585000
0%
b1110001 "
b1110001 <
b111 /
b111 9
b10000101 )
b10000101 8
b1110001 (
b1110001 7
b1111001 A
b111 @
b10000101 >
b1110001 =
b111 6
b1000010111100100100000110000101 5
b10111000100101111011111001110001 4
b10101 2
b111010 3
b1111000 -
1*
b101 D
b101010 C
b10111100 B
#595000
b1 "
b1 <
b10 /
b10 9
b111010 )
b111010 8
b111011 (
b111011 7
b1111010 A
b10 @
b111010 >
b111011 =
b10 6
b11101000001100011001100111010 5
b10011101110011000110000000111011 4
b10110 2
b111011 3
b1110001 -
0*
b111 D
b10000101 C
b1110001 B
#605000
1$
b11110101 "
b11110101 <
b1 /
b1 9
b11110001 )
b11110001 8
b10101 (
b10101 7
b1111011 A
b1 @
b11110001 >
b10101 =
b1 6
b1111000110110011001101111110001 5
b1010101010100100101100010101 4
b10111 2
b111100 3
b1 -
b10 D
b111010 C
b111011 B
#615000
0$
b1100010 "
b1100010 <
b111 /
b111 9
b1001100 )
b1001100 8
b1100010 (
b1100010 7
b1111100 A
b111 @
b1001100 >
b1100010 =
b111 6
b100110001101011111101101001100 5
b110001001000110000011101100010 4
b11000 2
b111101 3
1+
b11110101 -
b1 D
b11110001 C
b10101 B
#625000
1$
b11111111 "
b11111111 <
b1 /
b1 9
b11111000 )
b11111000 8
b10001111 (
b10001111 7
b1111101 A
b1 @
b11111000 >
b10001111 =
b1 6
b1111100011011011010100111111000 5
b1000111101110011010000110001111 4
b11001 2
b111110 3
0+
b1100010 -
b111 D
b1001100 C
b1100010 B
#635000
0$
1%
b111110 "
b111110 <
b101 /
b101 9
b1011100 )
b1011100 8
b10011111 (
b10011111 7
b1111110 A
b101 @
b1011100 >
b10011111 =
b101 6
b10101110011111011001010001011100 5
b11001111110001000101011010011111 4
b11010 2
b111111 3
1+
b11111111 -
b1 D
b11111000 C
b10001111 B
#645000
0%
b1001 "
b1001 <
b0 /
b0 9
b1001001 )
b1001001 8
b10001001 (
b10001001 7
b1111111 A
b0 @
b1001001 >
b10001001 =
b0 6
b10100100101011100011001001001001 5
b1000100110111100011011110001001 4
b11011 2
b1000000 3
0+
b111110 -
1*
b101 D
b1011100 C
b10011111 B
#655000
1%
b1101011 "
b1101011 <
b110 /
b110 9
b1010001 )
b1010001 8
b11010111 (
b11010111 7
b10000000 A
b110 @
b1010001 >
b11010111 =
b110 6
b10101000110001111111110001010001 5
b11101011111111101100000011010111 4
b11100 2
b1000001 3
b1001 -
0*
b0 D
b1001001 C
b10001001 B
#665000
1!
0%
b0 "
b0 <
b0 /
b0 9
b11000010 )
b11000010 8
b1100 (
b1100 7
b10000001 A
b0 @
b11000010 >
b1100 =
b0 6
b11100001001011001100111011000010 5
b110000111010111111100001100 4
b11101 2
b1000010 3
b1101011 -
1*
b110 D
b1010001 C
b11010111 B
#675000
0!
b1001010 "
b1001010 <
b10 /
b10 9
b111101 )
b111101 8
b1110111 (
b1110111 7
b10000010 A
b10 @
b111101 >
b1110111 =
b10 6
b11110111100101110110100111101 5
b10111011100000100101101001110111 4
b11110 2
b1000011 3
1.
b0 -
0*
b0 D
b11000010 C
b1100 B
#685000
b1111111 "
b1111111 <
b1 /
b1 9
b1101101 )
b1101101 8
b1111110 (
b1111110 7
b10000011 A
b1 @
b1101101 >
b1111110 =
b1 6
b110110111001011000000101101101 5
b10111111000001010000000001111110 4
b11111 2
b1000100 3
0.
b1001010 -
b10 D
b111101 C
b1110111 B
#695000
b111110 "
b111110 <
b101 /
b101 9
b11010011 )
b11010011 8
b11111 (
b11111 7
b10000100 A
b101 @
b11010011 >
b11111 =
b101 6
b11101001111010111111011011010011 5
b1111110100101000111100011111 4
b100000 2
b1000101 3
b1111111 -
b1 D
b1101101 C
b1111110 B
#705000
b1111011 "
b1111011 <
b1 /
b1 9
b1011011 )
b1011011 8
b1111000 (
b1111000 7
b10000101 A
b1 @
b1011011 >
b1111000 =
b1 6
b101101110110100101100101011011 5
b10111100000101001000100001111000 4
b100001 2
b1000110 3
b111110 -
b101 D
b11010011 C
b11111 B
#715000
b101010 "
b101010 <
b0 /
b0 9
b101010 )
b101010 8
b111111 (
b111111 7
b10000110 A
b0 @
b101010 >
b111111 =
b0 6
b10101000011001010111100101010 5
b10011111111100101010111000111111 4
b100010 2
b1000111 3
b1111011 -
b1 D
b1011011 C
b1111000 B
#725000
1$
b11111000 ;
b11111000 "
b11111000 <
b100 /
b100 9
b10001110 )
b10001110 8
b10000110 (
b10000110 7
b10000111 A
b100 @
b10001110 >
b10000110 =
b100 6
b11000111000110100000110010001110 5
b11000011001111110011100010000110 4
b100011 2
b1001000 3
b101010 -
b0 D
b101010 C
b111111 B
#735000
0$
1%
b100100000 ;
b100000 "
b100000 <
b11 /
b11 9
b100110 )
b100110 8
b11111010 (
b11111010 7
b10001000 A
b11 @
b100110 >
b11111010 =
b11 6
b10010011011111011011110000100110 5
b1111101001101011001100111111010 4
b100100 2
b1001001 3
1+
b11111000 -
b11111000 0
b100 D
b10001110 C
b10000110 B
#745000
1%
b0 ;
b1000110 "
b1000110 <
b101 /
b101 9
b101111 )
b101111 8
b10100011 (
b10100011 7
b10001001 A
b101 @
b101111 >
b10100011 =
b101 6
b10010111100110011010100000101111 5
b11010001100010111011010010100011 4
b100101 2
b1001010 3
0+
1*
b100000 -
b100100000 0
b11 D
b100110 C
b11111010 B
#755000
0%
b1011111 "
b1011111 <
b111 /
b111 9
b1000100 )
b1000100 8
b1011111 (
b1011111 7
b10001010 A
b111 @
b1000100 >
b1011111 =
b111 6
b100010001010010000110101000100 5
b10101111110110000101011001011111 4
b100110 2
b1001011 3
b1000110 -
b0 0
1*
b101 D
b101111 C
b10100011 B
#765000
b101101 "
b101101 <
b10 /
b10 9
b11100110 )
b11100110 8
b11001011 (
b11001011 7
b10001011 A
b10 @
b11100110 >
b11001011 =
b10 6
b11110011000010010001101011100110 5
b11100101100110110011011011001011 4
b100111 2
b1001100 3
b1011111 -
0*
b111 D
b1000100 C
b1011111 B
#775000
1%
b10100 "
b10100 <
b110 /
b110 9
b11101101 )
b11101101 8
b101001 (
b101001 7
b10001100 A
b110 @
b11101101 >
b101001 =
b110 6
b11110110100000101110001011101101 5
b10100110011111100000100101001 4
b101000 2
b1001101 3
b101101 -
b10 D
b11100110 C
b11001011 B
#785000
1$
0%
b11110101 "
b11110101 <
b1 /
b1 9
b10110101 )
b10110101 8
b1100101 (
b1100101 7
b10001101 A
b1 @
b10110101 >
b1100101 =
b1 6
b11011010100010101110001010110101 5
b10110010100111111011011001100101 4
b101001 2
b1001110 3
b10100 -
1*
b110 D
b11101101 C
b101001 B
#795000
0$
b1000000 "
b1000000 <
b0 /
b0 9
b1000100 )
b1000100 8
b1111001 (
b1111001 7
b10001110 A
b0 @
b1000100 >
b1111001 =
b0 6
b100010001100011111111101000100 5
b111100111100010001100101111001 4
b101010 2
b1001111 3
1+
b11110101 -
0*
b1 D
b10110101 C
b1100101 B
#805000
b10101 "
b10101 <
b110 /
b110 9
b10101011 )
b10101011 8
b101010 (
b101010 7
b10001111 A
b110 @
b10101011 >
b101010 =
b110 6
b1010101111101101010110110101011 5
b10101000010010000101100101010 4
b101011 2
b1010000 3
0+
b1000000 -
b0 D
b1000100 C
b1111001 B
